{
    "type": "minecraft:empty",
    "pools": [
        {
            "rolls": 1,
            "entries": [
                {
                    "type": "minecraft:item",
                    "name": "minecraft:crossbow",
                    "functions": [
                        {
                            "function": "minecraft:set_components",
                            "components": {
                                "lore": [
                                    {
                                        "translate": "item.energy_blaster.lore.0"
                                    },
                                    {
                                        "translate": "item.energy_blaster.lore.1"
                                    },
                                    {
                                        "translate": "item.energy_blaster.lore.2"
                                    }
                                ],
                                "custom_name": {
                                    "translate": "item.energy_blaster.name"
                                },
                                "custom_data": {
                                    "item": "energy_blaster",
                                    "itemRarity": 3,
                                    "itemType": 2
                                },
                                "enchantments": {
                                    "quick_charge": 2
                                },
                                "tooltip_style": "minecraft:epic/ranged"
                            }
                        }
                    ]
                }
            ]
        }
    ]
}
