{
    "criteria":
    {
        "right_click":
        {
            "trigger": "minecraft:using_item",
            "conditions":
            {
                "item":
                {
                    "items": 
                    [
                        "minecraft:glow_item_frame"
                    ],
                    "predicates": 
                    {
                        "minecraft:custom_data":
                        {
                            "item":"diy_repair_kit"
                        }
                    }
                }
            }
        }
    },
    "requirements":
    [
        [
            "right_click"
        ]
    ],
    "rewards":
    {
        "function": "it:tech/active/diy_repair_kit/right_click"
    }
}