{
    "type": "minecraft:empty",
    "pools": [
        {
            "rolls": 1,
            "entries": [
                {
                    "type": "minecraft:item",
                    "name": "minecraft:light_gray_dye",
                    "functions": [
                        {
                            "function": "minecraft:set_components",
                            "components": {
                                "lore": [
                                    {
                                        "translate": "item.contrary_wind.lore.0"
                                    },
                                    {
                                        "translate": "item.contrary_wind.lore.1"
                                    },
                                    {
                                        "translate": "item.contrary_wind.lore.2"
                                    },
                                    {
                                        "translate": "item.contrary_wind.lore.3"
                                    }
                                ],
                                "custom_name": {
                                    "translate": "item.contrary_wind.name"
                                },
                                "custom_data": {
                                    "item": "contrary_wind",
                                    "itemRarity": 1,
                                    "itemType": 1
                                },
                                "max_stack_size": 1,
                                "item_model": "minecraft:wind_charge",
                                "tooltip_style": "minecraft:uncommon/passive"
                            }
                        }
                    ]
                }
            ]
        }
    ]
}
