{
    "criteria":
    {
        "right_click":
        {
            "trigger": "minecraft:using_item",
            "conditions":
            {
                "item":
                {
                    "predicates": 
                    {
                        "minecraft:custom_data":
                        {
                            "item":"sans_pointer_2000"
                        }
                    }
                }
            }
        }
    },
    "requirements":
    [
        [
            "right_click"
        ]
    ],
    "rewards":
    {
        "function": "it:tech/debug/sans_pointer_2000/right_click"
    }
}